setup.py
Pawopy.egg-info/PKG-INFO
Pawopy.egg-info/SOURCES.txt
Pawopy.egg-info/dependency_links.txt
Pawopy.egg-info/requires.txt
Pawopy.egg-info/top_level.txt
pawopy/__init__.py
pawopy/handler.py
pawopy/mastodon.py
pawopy/model.py
pawopy/stream.py