Metadata-Version: 1.0
Name: Pawopy
Version: 0.0.3
Summary: A Python wrapper for the Mastodon API
Home-page: https://github.com/calmery/Pawopy
Author: calmery
Author-email: contact@calmery.me
License: MIT
Keywords: mastodon api mstdn pawoo
Platform: UNKNOWN
